dashed/__init__.py
dashed/__main__.py
dashed/discord.py
dashed/interaction.py
dashed/loader.py
dashed/module.py
dashed/server.py
dashed-0.1.0.dist-info/WHEEL
dashed-0.1.0.dist-info/METADATA
dashed-0.1.0.dist-info/RECORD
