Metadata-Version: 2.1
Name: dashed
Version: 0.1.0
Summary: 
Author: andrei
Author-email: b1naryth1ef@gmail.com
Requires-Python: >=3.8,<4.0
Classifier: Programming Language :: Python :: 3
Classifier: Programming Language :: Python :: 3.8
Classifier: Programming Language :: Python :: 3.9
Requires-Dist: PyNaCl (>=1.4.0,<2.0.0)
Requires-Dist: aiohttp (>=3.7.4,<4.0.0)
Requires-Dist: httpx (>=0.18.2,<0.19.0)
